onlinopy/__init__.py
onlinopy-0.0.1.dist-info/LICENSE
onlinopy-0.0.1.dist-info/METADATA
onlinopy-0.0.1.dist-info/WHEEL
onlinopy-0.0.1.dist-info/top_level.txt
onlinopy-0.0.1.dist-info/RECORD
