Metadata-Version: 2.1
Name: onlinopy
Version: 0.0.1
Summary: This package will be available soon!
Home-page: https://onlino.xyz
Author: Meyer
License: UNKNOWN
Platform: UNKNOWN
Classifier: Programming Language :: Python :: 3
Classifier: License :: OSI Approved :: Apache Software License
Classifier: Operating System :: OS Independent
Requires-Python: >=3.5
